carabiner/__init__.py
carabiner/revenue.py
carabiner/status_1.py
carabiner/_clique/__init__.py
carabiner/_clique/group/__init__.py
carabiner/_status/insurance.proc.py
carabiner/_status/insurance_clouds.proc.py
carabiner/autopilot/bt/strategies/example_1.py
carabiner/climate/__init__.py
carabiner/clouds/Alpaca/shares/retrieve.py
carabiner/clouds/Alpaca/shares/structure_1.py
carabiner/clouds/Alpaca/shares/_status/API_status_1.py
carabiner/clouds/CCXT/__init__.py
carabiner/clouds/CCXT/OHLCV/__init__.py
carabiner/clouds/CCXT/OHLCV/candles/__init__.py
carabiner/clouds/CCXT/OHLCV/candles_v1/__init__.py
carabiner/clouds/CCXT/symbols/array.py
carabiner/clouds/Coinbase/API/__init__.py
carabiner/clouds/Coinbase/API/build_JWT.py
carabiner/clouds/Coinbase/API/accounts/__init__.py
carabiner/clouds/Coinbase/API/orders/order_IDs.py
carabiner/clouds/Coinbase/API/products/candles.py
carabiner/clouds/Coinbase/API/products/catalogue.py
carabiner/clouds/Coinbase/orders/place.py
carabiner/clouds/Tradier/_status/API_status_combine_1.py
carabiner/clouds/Tradier/procedures/options/combine.py
carabiner/clouds/Tradier/v1/markets/options/chains/__init__.py
carabiner/clouds/Tradier/v1/markets/options/chains/parse_1.py
carabiner/clouds/Tradier/v1/markets/options/expirations/__init__.py
carabiner/clouds/TradingView/sensors/__init__.py
carabiner/clouds/Yahoo/retrieve.py
carabiner/gadgets/format_percentage.py
carabiner/gadgets/ratio.py
carabiner/gadgets/clock/UTC/ISO.py
carabiner/gadgets/clock/UTC/greatness_1.py
carabiner/gadgets/math/slope/__init__.py
carabiner/gadgets/pandas/DF/from_list.py
carabiner/gadgets/pandas/DF/to_list.py
carabiner/gadgets/pandas/DF/_status/status_from_1.py
carabiner/gadgets/summation/__init__.py
carabiner/gadgets/summation/status_1.py
carabiner/groups/USA/forms/SEC/6K/__init__.py
carabiner/groups/USA/forms/balance_sheets/__init__.py
carabiner/groups/USA/forms/balance_sheets/equity/__init__.py
carabiner/groups/USA/forms/income/__init__.py
carabiner-1.0.0.dist-info/METADATA
carabiner-1.0.0.dist-info/WHEEL
carabiner-1.0.0.dist-info/entry_points.txt
carabiner-1.0.0.dist-info/top_level.txt
carabiner-1.0.0.dist-info/RECORD
