Metadata-Version: 2.1
Name: carabiner
Version: 1.0.0
Summary: economic estimation
License: GPL 3.0 + CC BY-NC-SA 4.0
Keywords: economic estimation,finance,commerce,wealth,money,treasures,treasury,subconscious trading
Requires-Dist: bracelet
Requires-Dist: ships
Requires-Dist: alpaca-py
Requires-Dist: arrow
Requires-Dist: backtrader
Requires-Dist: basana
Requires-Dist: botanical
Requires-Dist: cufflinks
Requires-Dist: cryptography
Requires-Dist: ccxt
Requires-Dist: clique
Requires-Dist: dash
Requires-Dist: finvizfinance
Requires-Dist: ipychart
Requires-Dist: lumibot
Requires-Dist: matplotlib
Requires-Dist: numpy
Requires-Dist: pandas
Requires-Dist: pandas-ta
Requires-Dist: pandas-datareader
Requires-Dist: plotly
Requires-Dist: pydash
Requires-Dist: PyJSONViewer
Requires-Dist: PyJWT
Requires-Dist: stock-indicators
Requires-Dist: ta
Requires-Dist: talipp
Requires-Dist: technical-indicators-lib
Requires-Dist: tradingview-ta
Requires-Dist: tradingview-screener
Requires-Dist: yahooquery
Requires-Dist: yfinance
